nonebot_plugin_escape_url/__init__.py
nonebot_plugin_escape_url/config.py
nonebot_plugin_escape_url/core.py
nonebot_plugin_escape_url/onebot_v11.py
nonebot_plugin_escape_url/qq.py
nonebot_plugin_escape_url-0.1.5.post1.dist-info/METADATA
nonebot_plugin_escape_url-0.1.5.post1.dist-info/WHEEL
nonebot_plugin_escape_url-0.1.5.post1.dist-info/RECORD
